Metadata-Version: 2.1
Name: carlagodinholistalbumsbeatles
Version: 0.0.1
Summary: Shows the list of The Beatles Albums
Home-page: 
Author: Carla Sónia Godinho
Author-email: carlasoniagodinho4@gmail.com
License: MIT
Keywords: list albums
Classifier: Development Status :: 5 - Production/Stable
Classifier: Intended Audience :: Education
Classifier: Operating System :: Microsoft :: Windows :: Windows 11
Classifier: License :: OSI Approved :: MIT License
Classifier: Programming Language :: Python :: 3.11
License-File: LICENSE.txt
